napalm_slx_os/__init__.py
napalm_slx_os/slx_os.py
napalm_slx_os/utils/textfsm_templates/show_arp.tpl
napalm_slx_os/utils/textfsm_templates/show_inventory_chassis.tpl
napalm_slx_os/utils/textfsm_templates/show_ip_bgp_neighbors.tpl
napalm_slx_os/utils/textfsm_templates/show_ip_bgp_summary.tpl
napalm_slx_os/utils/textfsm_templates/show_ipv6_bgp_neighbors.tpl
napalm_slx_os/utils/textfsm_templates/show_ipv6_bgp_summary.tpl
napalm_slx_os/utils/textfsm_templates/show_version.tpl
napalm_slx_os/utils/textfsm_templates/show_vrf.tpl
napalm_slx_os-0.2.0.dist-info/LICENSE
napalm_slx_os-0.2.0.dist-info/METADATA
napalm_slx_os-0.2.0.dist-info/WHEEL
napalm_slx_os-0.2.0.dist-info/top_level.txt
napalm_slx_os-0.2.0.dist-info/RECORD
